Modulos/__init__.py
Modulos/azure.py
Modulos/cloud.py
Modulos/gcp.py
brunotanakastonecli-0.2.data/scripts/stone_cli
brunotanakastonecli-0.2.dist-info/METADATA
brunotanakastonecli-0.2.dist-info/WHEEL
brunotanakastonecli-0.2.dist-info/top_level.txt
brunotanakastonecli-0.2.dist-info/RECORD
